pulumi_cloudinit/__init__.py
pulumi_cloudinit/_inputs.py
pulumi_cloudinit/_utilities.py
pulumi_cloudinit/config.py
pulumi_cloudinit/get_config.py
pulumi_cloudinit/outputs.py
pulumi_cloudinit/provider.py
pulumi_cloudinit/pulumi-plugin.json
pulumi_cloudinit/py.typed
pulumi_cloudinit-1.4.15.dist-info/METADATA
pulumi_cloudinit-1.4.15.dist-info/WHEEL
pulumi_cloudinit-1.4.15.dist-info/top_level.txt
pulumi_cloudinit-1.4.15.dist-info/RECORD
